scuttlebutt/__init__.py
scuttlebutt/protocol.py
scuttlebutt/server.py
scuttlebutt-0.1.dist-info/METADATA
scuttlebutt-0.1.dist-info/RECORD
scuttlebutt-0.1.dist-info/WHEEL
scuttlebutt-0.1.dist-info/top_level.txt
