Metadata-Version: 2.1
Name: scuttlebutt
Version: 0.1
Summary: Implementation of the the Secure Scuttlebutt protocol.
Home-page: https://github.com/supakeen/scuttlebutt
Author: supakeen
Author-email: cmdr@supakeen.com
License: UNKNOWN
Platform: UNKNOWN
Requires-Dist: cryptography
